[
  {
    "group": "common",
    "rows": [
      [
        {
          "name": "Major",
          "shortname": "M",
          "scaleType": "Diatonic",
          "mode": 0,
          "scaleTheme": 0,
          "sid" : 1
        },
        {
          "name": "Minor",
          "shortname": "m",
          "scaleType": "Diatonic",
          "mode": 5,
          "scaleTheme": 0,
          "sid" : 2
        },
        {
          "name": "Major Pentatonic",
          "shortname": "M p",
          "scaleType": "Pentatonic",
          "mode": 0,
          "scaleTheme": 0,
          "sid" : 3
        },
        {
          "name": "Minor Pentatonic",
          "shortname": "m p",
          "scaleType": "Pentatonic",
          "mode": 4,
          "scaleTheme": 0,
          "sid" : 4
        }
      ],
      [
        {
          "name": "Major (highlight on 3 & 5)",
          "shortname": "M+",
          "scaleType": "Diatonic",
          "mode": 0,
          "scaleTheme": 1,
          "sid" : 5
        },
        {
          "name": "Minor (highlight on 3 & 5)",
          "shortname": "m+",
          "scaleType": "Diatonic",
          "mode": 5,
          "scaleTheme": 1,
          "sid" : 6
        },
        {
          "name": "Major (highlight on pentatonic notes)",
          "shortname": "M+p",
          "scaleType": "Diatonic",
          "mode": 0,
          "scaleTheme": 2,
          "sid" : 7
        },
        {
          "name": "Minor (highlight on pentatonic notes)",
          "shortname": "m+p",
          "scaleType": "Diatonic",
          "mode": 5,
          "scaleTheme": 3,
          "sid" : 8
        }
      ]
    ]
  },
  {
    "group": "modes",
    "rows": [
      [
        {
          "name": "Ionian (Major)",
          "shortname": "Io",
          "scaleType": "Diatonic",
          "mode": 0,
          "scaleTheme": 0,
          "sid" : 9
        },
        {
          "name": "Dorian",
          "shortname": "Do",
          "scaleType": "Diatonic",
          "mode": 1,
          "scaleTheme": 0,
          "sid" : 10
        },
        {
          "name": "Phrygian",
          "shortname": "Ph",
          "scaleType": "Diatonic",
          "mode": 2,
          "scaleTheme": 0,
          "sid" : 11
        },
        {
          "name": "Lydian",
          "shortname": "Ly",
          "scaleType": "Diatonic",
          "mode": 3,
          "scaleTheme": 0,
          "sid" : 12
        },
        {
          "name": "Mixolydian",
          "shortname": "Mi",
          "scaleType": "Diatonic",
          "mode": 4,
          "scaleTheme": 0,
          "sid" : 13
        },
        {
          "name": "Aeolian (Natural Minor)",
          "shortname": "Ae",
          "scaleType": "Diatonic",
          "mode": 5,
          "scaleTheme": 0,
          "sid" : 14
        },
        {
          "name": "Locrian",
          "shortname": "Lo",
          "scaleType": "Diatonic",
          "mode": 6,
          "scaleTheme": 0,
          "sid" : 15
        }
      ],
      [
        {
          "name": "Ionian (No colour notes, but highlights on 3 & 5)",
          "shortname": "Io+",
          "scaleType": "Diatonic",
          "mode": 0,
          "scaleTheme": 1,
          "sid" : 16
        },
        {
          "name": "Dorian (colour notes: ♭3, ♭7)",
          "shortname": "Do+",
          "scaleType": "Diatonic",
          "mode": 1,
          "scaleTheme": 4,
          "sid" : 17
        },
        {
          "name": "Phrygian (colour notes: ♭2, ♭3, ♭6, ♭7)",
          "shortname": "Ph+",
          "scaleType": "Diatonic",
          "mode": 2,
          "scaleTheme": 5,
          "sid" : 18
        },
        {
          "name": "Lydian (colour notes: ♯4)",
          "shortname": "Ly+",
          "scaleType": "Diatonic",
          "mode": 3,
          "scaleTheme": 6,
          "sid" : 19
        },
        {
          "name": "Mixolydian (colour notes: ♭7)",
          "shortname": "Mi+",
          "scaleType": "Diatonic",
          "mode": 4,
          "scaleTheme": 7,
          "sid" : 20
        },
        {
          "name": "Aeolian (colour notes: ♭3, ♭6, ♭7)",
          "shortname": "Ae+",
          "scaleType": "Diatonic",
          "mode": 5,
          "scaleTheme": 8,
          "sid" : 21
        },
        {
          "name": "Locrian (colour notes: ♭2, ♭3, ♭5, ♭6, ♭7)",
          "shortname": "Lo+",
          "scaleType": "Diatonic",
          "mode": 6,
          "scaleTheme": 9,
          "sid" : 22
        }
      ]
    ]
  },
  {
    "group": "other",
    "rows": [
      [
        {
          "name": "Ionian (Major)",
          "shortname": "Hi",
          "scaleType": "Diatonic",
          "mode": 1,
          "scaleTheme": 0,
          "sid" : 23
        },
        {
          "name": "Dorian",
          "shortname": "Po",
          "scaleType": "Diatonic",
          "mode": 2,
          "scaleTheme": 0,
          "sid" : 24
        }
      ],
      [
        {
          "name": "Ionian (No colour notes, but highlights on 3 & 5)",
          "shortname": "St",
          "scaleType": "Diatonic",
          "mode": 1,
          "scaleTheme": 4,
          "sid" : 25
        },
        {
          "name": "Dorian (colour notes: ♭3, ♭7)",
          "shortname": "Ej",
          "scaleType": "Diatonic",
          "mode": 2,
          "scaleTheme": 4,
          "sid" : 26
        }
      ]
    ]
  }
]